plus/__init__.py
plus/__main__.py
plus/actions.py
plus/compiler.py
plus/default_files.py
plus/dependency.py
plus/project.py
plus/repository.py
plus_cpp-0.8.0.dist-info/LICENSE
plus_cpp-0.8.0.dist-info/METADATA
plus_cpp-0.8.0.dist-info/WHEEL
plus_cpp-0.8.0.dist-info/entry_points.txt
plus_cpp-0.8.0.dist-info/top_level.txt
plus_cpp-0.8.0.dist-info/RECORD
