Metadata-Version: 2.1
Name: plus-cpp
Version: 0.8.0
Summary: Plus is a library for managing c++ projects
Home-page: https://github.com/darilrt/plus
Author: Daril Rodriguez
Author-email: darilrodriguez.2@gmail.com
License: MIT License
License-File: LICENSE
